Metadata-Version: 2.1
Name: luckstring
Version: 1.0.0
Summary: a string split fuction,like split() then ignore case.
Home-page: https://pypi.org/project/luckstring/#description
Author: goblinintree
Author-email: goblinintree@126.com
License: MIT
Keywords: split,string,luck,luckstring
Platform: all
Classifier: Environment :: Web Environment
Classifier: License :: OSI Approved :: MIT License
Classifier: Operating System :: Microsoft
Classifier: Programming Language :: Python :: 3.7
